{"name":"Ingresar a Elements","id":"evaluar-elements;ingresar-a-elements","testSteps":[{"number":1,"description":"Given \"Actor\" Desea navegar a la pagina \"https://demoqa.com/\"","duration":10948,"startTime":"2023-01-10T20:42:56.515301-05:00[America/Bogota]","screenshots":[{"screenshot":"7c26849ec3565f1b3dccb66e1e4cdddabd9f4537d7f87fa410f029362da1203d.png","timeStamp":1673401387463}],"result":"SUCCESS","precondition":false,"level":0,"children":[{"number":2,"description":"Actor opens the https://demoqa.com/","duration":10446,"startTime":"2023-01-10T20:42:56.985130-05:00[America/Bogota]","screenshots":[{"screenshot":"7c26849ec3565f1b3dccb66e1e4cdddabd9f4537d7f87fa410f029362da1203d.png","timeStamp":1673401387430}],"result":"SUCCESS","precondition":false,"level":1}]},{"number":3,"description":"When Crear un nuevo registro en Web tables","duration":10561,"startTime":"2023-01-10T20:43:07.465494-05:00[America/Bogota]","screenshots":[{"screenshot":"c025a35e8d1a67a7e6987cfd38954bbcb6c8097c5357e8294f827392b2a3d740.png","timeStamp":1673401398026}],"result":"SUCCESS","precondition":false,"level":0,"children":[{"number":4,"description":"Actor new elements","duration":9094,"startTime":"2023-01-10T20:43:08.926009-05:00[America/Bogota]","screenshots":[{"screenshot":"c025a35e8d1a67a7e6987cfd38954bbcb6c8097c5357e8294f827392b2a3d740.png","timeStamp":1673401398020}],"result":"SUCCESS","precondition":false,"level":1,"children":[{"number":5,"description":"Actor clicks on Boton elements","duration":1194,"startTime":"2023-01-10T20:43:09.525131-05:00[America/Bogota]","screenshots":[{"screenshot":"de71ff95b824fe6857da51a5b64e37e56800433c72ab679c27c49a9dc6d02a6d.png","timeStamp":1673401390719}],"result":"SUCCESS","precondition":false,"level":2},{"number":6,"description":"Actor clicks on Boton Web table","duration":782,"startTime":"2023-01-10T20:43:10.723391-05:00[America/Bogota]","screenshots":[{"screenshot":"de71ff95b824fe6857da51a5b64e37e56800433c72ab679c27c49a9dc6d02a6d.png","timeStamp":1673401390735},{"screenshot":"d0b9f37a3d5f9108b0432749e74466b52b130a4c60e5b1abc60e6a03385fffb0.png","timeStamp":1673401391505}],"result":"SUCCESS","precondition":false,"level":2},{"number":7,"description":"Actor clicks on Boton Add","duration":716,"startTime":"2023-01-10T20:43:11.508488-05:00[America/Bogota]","screenshots":[{"screenshot":"d0b9f37a3d5f9108b0432749e74466b52b130a4c60e5b1abc60e6a03385fffb0.png","timeStamp":1673401391521},{"screenshot":"04d11aed064bc4aacf85db161536a009c074670247d5fba61e5eb6d620ffd7b3.png","timeStamp":1673401392225}],"result":"SUCCESS","precondition":false,"level":2},{"number":8,"description":"Actor clicks on Agregar nombre","duration":595,"startTime":"2023-01-10T20:43:12.227860-05:00[America/Bogota]","screenshots":[{"screenshot":"04d11aed064bc4aacf85db161536a009c074670247d5fba61e5eb6d620ffd7b3.png","timeStamp":1673401392238},{"screenshot":"8042a84059d24c54806bbf84ad4181a96640ea975816c59be52e0492706f4caa.png","timeStamp":1673401392823}],"result":"SUCCESS","precondition":false,"level":2},{"number":9,"description":"Actor enters \u0027Santiago\u0027 then hits [TAB] into Agregar nombre","duration":846,"startTime":"2023-01-10T20:43:12.826356-05:00[America/Bogota]","screenshots":[{"screenshot":"8042a84059d24c54806bbf84ad4181a96640ea975816c59be52e0492706f4caa.png","timeStamp":1673401392838},{"screenshot":"87be6afc1eaa10753016a6635023cae54f21cb19d43b4945032a9331e56dfe15.png","timeStamp":1673401393672}],"result":"SUCCESS","precondition":false,"level":2},{"number":10,"description":"Actor enters \u0027Renteria\u0027 then hits [TAB] into Agregar apellido","duration":794,"startTime":"2023-01-10T20:43:13.675728-05:00[America/Bogota]","screenshots":[{"screenshot":"87be6afc1eaa10753016a6635023cae54f21cb19d43b4945032a9331e56dfe15.png","timeStamp":1673401393687},{"screenshot":"9e4636494b9a6271661f8ed15d98f21f4d5c259f9119a1af78bbb22a5e43c517.png","timeStamp":1673401394470}],"result":"SUCCESS","precondition":false,"level":2},{"number":11,"description":"Actor enters \u0027san.ren@gmail.com\u0027 then hits [TAB] into Agregar email","duration":809,"startTime":"2023-01-10T20:43:14.472890-05:00[America/Bogota]","screenshots":[{"screenshot":"9e4636494b9a6271661f8ed15d98f21f4d5c259f9119a1af78bbb22a5e43c517.png","timeStamp":1673401394483},{"screenshot":"44271547b7d40246112386ad7a1b3b8452c9eb75bd0c353d81fe5d289c5e9695.png","timeStamp":1673401395282}],"result":"SUCCESS","precondition":false,"level":2},{"number":12,"description":"Actor enters \u002730\u0027 then hits [TAB] into Agregar edad","duration":686,"startTime":"2023-01-10T20:43:15.285380-05:00[America/Bogota]","screenshots":[{"screenshot":"44271547b7d40246112386ad7a1b3b8452c9eb75bd0c353d81fe5d289c5e9695.png","timeStamp":1673401395294},{"screenshot":"84ee05c591c5361d7cf348643c7315ea465334bd0fd2dea75ec1f5ae580d42c9.png","timeStamp":1673401395972}],"result":"SUCCESS","precondition":false,"level":2},{"number":13,"description":"Actor enters \u00271000\u0027 then hits [TAB] into Agregar salario","duration":696,"startTime":"2023-01-10T20:43:15.974027-05:00[America/Bogota]","screenshots":[{"screenshot":"84ee05c591c5361d7cf348643c7315ea465334bd0fd2dea75ec1f5ae580d42c9.png","timeStamp":1673401395982},{"screenshot":"4bda146b1dd0cc687747c7728c14baaf49bd57080ca881ff4aa9fa36339584e0.png","timeStamp":1673401396670}],"result":"SUCCESS","precondition":false,"level":2},{"number":14,"description":"Actor enters \u0027QA\u0027 then hits TAB and ENTER into Agregar departamento","duration":794,"startTime":"2023-01-10T20:43:16.672429-05:00[America/Bogota]","screenshots":[{"screenshot":"4bda146b1dd0cc687747c7728c14baaf49bd57080ca881ff4aa9fa36339584e0.png","timeStamp":1673401396680},{"screenshot":"01004bc65f9547cf493e01653b8b9589ee11c04f1768751a8be6b4c6973f3d05.png","timeStamp":1673401397466}],"result":"SUCCESS","precondition":false,"level":2},{"number":15,"description":"Actor clicks on Eliminar Elemento","duration":542,"startTime":"2023-01-10T20:43:17.468958-05:00[America/Bogota]","screenshots":[{"screenshot":"01004bc65f9547cf493e01653b8b9589ee11c04f1768751a8be6b4c6973f3d05.png","timeStamp":1673401397477},{"screenshot":"c025a35e8d1a67a7e6987cfd38954bbcb6c8097c5357e8294f827392b2a3d740.png","timeStamp":1673401398011}],"result":"SUCCESS","precondition":false,"level":2}]}]},{"number":16,"description":"Then Valida que se creo el registro \"Santiago\"","duration":880,"startTime":"2023-01-10T20:43:18.027692-05:00[America/Bogota]","screenshots":[{"screenshot":"3394bb9918ad2b8c7ac163d71de1493fcd6bd2fc788429b955415b57da7f8e41.png","timeStamp":1673401398908}],"result":"SUCCESS","precondition":false,"level":0,"children":[{"number":17,"description":"Then validate text should be \u0027Santiago\u0027","duration":767,"startTime":"2023-01-10T20:43:18.130689-05:00[America/Bogota]","screenshots":[{"screenshot":"3394bb9918ad2b8c7ac163d71de1493fcd6bd2fc788429b955415b57da7f8e41.png","timeStamp":1673401398478},{"screenshot":"3394bb9918ad2b8c7ac163d71de1493fcd6bd2fc788429b955415b57da7f8e41.png","timeStamp":1673401398898}],"result":"SUCCESS","precondition":false,"level":1}]}],"userStory":{"id":"evaluar-elements","storyName":"Evaluar elements","path":"elements.feature","narrative":"    Yo como automatizador de pruebas\n    Necesito ingresar a la pagina\n    Para validar algunas funcionalidades","type":"feature"},"featureTag":{"name":"Evaluar elements","type":"feature","displayName":"Evaluar elements"},"title":"Ingresar a Elements","description":"","tags":[{"name":"Punto1","type":"tag","displayName":"Punto1"}],"startTime":"2023-01-10T20:42:56.298262-05:00[America/Bogota]","duration":22612,"projectKey":"","sessionId":"ef01267b1be1f0b2242571075cdbc431","driver":"chrome:actor","isManualTestingUpToDate":false,"manual":false,"testSource":"Cucumber","actors":[{"name":"Actor","can":["browse the web"]}],"result":"SUCCESS"}